{
  "header": {
    "store": {
      "name": "store",
      "title": "Store",
      "route": "/store",
      "icon": "",
      "subMenu": [
        {
          "title": "스토어",
          "name": "store",
          "icon": "",
          "parent": "store",
          "route": "/store"
        },
        {
          "title": "구매내역",
          "name": "buylist",
          "icon": "",
          "parent": "store",
          "route": "/store/buylist"
        },
        {
          "title": "도메인 변경",
          "name": "storeChange",
          "icon": "",
          "parent": "store",
          "route": "/store/storeChange"
        },
        {
          "title": "계산서 신청",
          "name": "storetax",
          "icon": "",
          "parent": "store",
          "route": "/store/storetax"
        }
      ]
    },
    "works": {
      "name": "works",
      "title": "Works",
      "route": "/works",
      "icon": "",
      "subMenu": []
    },
    "service": {
      "name": "service",
      "title": "Service",
      "route": "/service",
      "icon": "",
      "subMenu": []
    },
    "supports": {
      "name": "supports",
      "title": "Supports",
      "route": "/supports",
      "icon": "",
      "subMenu": [
        {
          "title": "Supports",
          "name": "supports",
          "icon": "",
          "parent": "supports",
          "route": "/supports"
        },
        {
          "title": "공지사항",
          "name": "notice",
          "icon": "",
          "parent": "supports",
          "route": "/posts/notice"
        },
        {
          "title": "자주묻는 질문",
          "name": "faq",
          "icon": "",
          "parent": "supports",
          "route": "/posts/faq"
        }
      ]
    }
  },
  "footer": {
    "terms": {},
    "privacy": {},
    "about": {}
  }
}
